dsfinvk/__init__.py
dsfinvk/collection.py
dsfinvk/fields.py
dsfinvk/models.py
dsfinvk/table.py
dsfinvk/validate.py
dsfinvk-2.4.0.dist-info/LICENSE
dsfinvk-2.4.0.dist-info/METADATA
dsfinvk-2.4.0.dist-info/WHEEL
dsfinvk-2.4.0.dist-info/top_level.txt
dsfinvk-2.4.0.dist-info/RECORD
