Metadata-Version: 2.1
Name: dsfinvk
Version: 2.4.0
Summary: Digitale Schnittstelle der Finanzverwaltung fürKassensysteme
Home-page: https://github.com/pretix/python-dsfinvk
Author: Raphael Michel
Author-email: support@pretix.eu
License: Apache License
Keywords: germany fiscal export
Classifier: Intended Audience :: Developers
Classifier: Intended Audience :: Other Audience
Classifier: License :: OSI Approved :: Apache Software License
Classifier: Programming Language :: Python :: 3.4
Classifier: Programming Language :: Python :: 3.5
Classifier: Programming Language :: Python :: 3.6
License-File: LICENSE
Requires-Dist: pytz
